[{"player_id": 832, "team_id": 14, "country_id": 32, "position_id": 1, "common_name": "D. de Gea Quintana", "display_name": "David De Gea", "fullname": "David de Gea Quintana", "firstname": "David", "lastname": "de Gea Quintana", "nationality": "Spain", "birthdate": "07/11/1990", "birthcountry": "Spain", "birthplace": "Madrid", "height": "192 cm", "weight": "76 kg", "image_path": "https://cdn.sportmonks.com/images/soccer/players/0/832.png"}, {"player_id": 1947, "team_id": null, "country_id": 462, "position_id": 1, "common_name": "L. Grant", "display_name": "Lee Grant", "fullname": "Lee Grant", "firstname": "Lee", "lastname": "Grant", "nationality": "England", "birthdate": "27/01/1983", "birthcountry": "England", "birthplace": "Hemel Hempstead", "height": "193 cm", "weight": "83 kg", "image_path": "https://cdn.sportmonks.com/images/soccer/players/27/1947.png"}, {"player_id": 160206, "team_id": 14, "country_id": 47, "position_id": 2, "common_name": "V. Nilsson Lindel\u00f6f", "display_name": "Victor Lindel\u00f6f", "fullname": "Victor Nilsson Lindel\u00f6f", "firstname": "Victor", "lastname": "Nilsson Lindel\u00f6f", "nationality": "Sweden", "birthdate": "17/07/1994", "birthcountry": "Sweden", "birthplace": "V\u00e4ster\u00e5s", "height": "187 cm", "weight": "80 kg", "image_path": "https://cdn.sportmonks.com/images/soccer/players/14/160206.png"}, {"player_id": 1849, "team_id": 238858, "country_id": 23, "position_id": 2, "common_name": "E. Bailly", "display_name": "Eric Bailly", "fullname": "Eric Bertrand Bailly", "firstname": "Eric Bertrand", "lastname": "Bailly", "nationality": "C\u00f4te d'Ivoire", "birthdate": "12/04/1994", "birthcountry": "C\u00f4te d'Ivoire", "birthplace": "Bingerville", "height": "187 cm", "weight": "77 kg", "image_path": "https://cdn.sportmonks.com/images/soccer/players/25/1849.png"}, {"player_id": 433, "team_id": 14, "country_id": 462, "position_id": 2, "common_name": "P. Jones", "display_name": "Phil Jones", "fullname": "Phil Jones", "firstname": "Phil", "lastname": "Jones", "nationality": "England", "birthdate": "21/02/1992", "birthcountry": "England", "birthplace": "Preston", "height": "180 cm", "weight": "71 kg", "image_path": "https://cdn.sportmonks.com/images/soccer/players/17/433.png"}, {"player_id": 2884, "team_id": 14, "country_id": 462, "position_id": 2, "common_name": "H. Maguire", "display_name": "Harry Maguire", "fullname": "Harry Maguire", "firstname": "Harry", "lastname": "Maguire", "nationality": "England", "birthdate": "05/03/1993", "birthcountry": "England", "birthplace": "Sheffield", "height": "194 cm", "weight": "100 kg", "image_path": "https://cdn.sportmonks.com/images/soccer/players/4/2884.png"}, {"player_id": 955, "team_id": 14, "country_id": 462, "position_id": 2, "common_name": "L. Shaw", "display_name": "Luke Shaw", "fullname": "Luke Shaw", "firstname": "Luke", "lastname": "Shaw", "nationality": "England", "birthdate": "12/07/1995", "birthcountry": "England", "birthplace": "Kingston upon Thames", "height": "185 cm", "weight": "75 kg", "image_path": "https://cdn.sportmonks.com/images/soccer/players/27/955.png"}, {"player_id": 5252, "team_id": 14, "country_id": 462, "position_id": 2, "common_name": "A. Wan-Bissaka", "display_name": "Aaron Wan-Bissaka", "fullname": "Aaron Wan-Bissaka", "firstname": "Aaron", "lastname": "Wan-Bissaka", "nationality": "England", "birthdate": "26/11/1997", "birthcountry": "England", "birthplace": "London", "height": "183 cm", "weight": "72 kg", "image_path": "https://cdn.sportmonks.com/images/soccer/players/4/5252.png"}, {"player_id": 4391, "team_id": 14, "country_id": 462, "position_id": 2, "common_name": "A. Tuanzebe", "display_name": "Axel Tuanzebe", "fullname": "Axel Tuanzebe", "firstname": "Axel", "lastname": "Tuanzebe", "nationality": "England", "birthdate": "14/11/1997", "birthcountry": "Congo DR", "birthplace": "Bunia", "height": "182 cm", "weight": "75 kg", "image_path": "https://cdn.sportmonks.com/images/soccer/players/7/4391.png"}, {"player_id": 4536527, "team_id": 14, "country_id": 462, "position_id": 2, "common_name": "B. Williams", "display_name": "Brandon Williams", "fullname": "Brandon Williams", "firstname": "Brandon", "lastname": "Williams", "nationality": "England", "birthdate": "03/09/2000", "birthcountry": "England", "birthplace": null, "height": null, "weight": null, "image_path": "https://cdn.sportmonks.com/images/soccer/players/15/4536527.png"}, {"player_id": 1992, "team_id": 625, "country_id": 17, "position_id": 3, "common_name": "P. Pogba", "display_name": "Paul Pogba", "fullname": "Paul Pogba", "firstname": "Paul", "lastname": "Pogba", "nationality": "France", "birthdate": "15/03/1993", "birthcountry": "France", "birthplace": "Langny-sur-Marne", "height": "191 cm", "weight": "84 kg", "image_path": "https://cdn.sportmonks.com/images/soccer/players/8/1992.png"}, {"player_id": 846, "team_id": 34, "country_id": 32, "position_id": 3, "common_name": "J. Mata Garc\u00eda", "display_name": "Juan Mata", "fullname": "Juan Manuel Mata Garc\u00eda", "firstname": "Juan Manuel", "lastname": "Mata Garc\u00eda", "nationality": "Spain", "birthdate": "28/04/1988", "birthcountry": "Spain", "birthplace": "Burgos", "height": "170 cm", "weight": "63 kg", "image_path": "https://cdn.sportmonks.com/images/soccer/players/14/846.png"}, {"player_id": 205411, "team_id": 14, "country_id": 5, "position_id": 3, "common_name": "F. Rodrigues Santos", "display_name": "Fred", "fullname": "Frederico Rodrigues Santos", "firstname": "Frederico", "lastname": "Rodrigues Santos", "nationality": "Brazil", "birthdate": "05/03/1993", "birthcountry": "Brazil", "birthplace": "Belo Horizonte", "height": "169 cm", "weight": "64 kg", "image_path": "https://cdn.sportmonks.com/images//soccer/players/3/205411.png"}, {"player_id": 129602, "team_id": 14, "country_id": 20, "position_id": 3, "common_name": "B. Borges Fernandes", "display_name": "Bruno Fernandes", "fullname": "Bruno Miguel Borges Fernandes", "firstname": "Bruno Miguel", "lastname": "Borges Fernandes", "nationality": "Portugal", "birthdate": "08/09/1994", "birthcountry": "Portugal", "birthplace": "Maia", "height": "173 cm", "weight": "80 kg", "image_path": "https://cdn.sportmonks.com/images/soccer/players/2/129602.png"}, {"player_id": 5149, "team_id": 11, "country_id": 515, "position_id": 4, "common_name": "D. James", "display_name": "Daniel James", "fullname": "Daniel James", "firstname": "Daniel", "lastname": "James", "nationality": "Wales", "birthdate": "10/11/1997", "birthcountry": "England", "birthplace": "Kingston upon Hull", "height": "170 cm", "weight": "76 kg", "image_path": "https://cdn.sportmonks.com/images/soccer/players/29/5149.png"}, {"player_id": 1335, "team_id": 37, "country_id": 296, "position_id": 3, "common_name": "N. Mati\u0107", "display_name": "Nemanja Mati\u0107", "fullname": "Nemanja Mati\u0107", "firstname": "Nemanja", "lastname": "Mati\u0107", "nationality": "Serbia", "birthdate": "01/08/1988", "birthcountry": "Serbia", "birthplace": "\u0160abac", "height": "194 cm", "weight": "85 kg", "image_path": "https://cdn.sportmonks.com/images/soccer/players/23/1335.png"}, {"player_id": 455376, "team_id": 14, "country_id": 1161, "position_id": 3, "common_name": "S. McTominay", "display_name": "Scott McTominay", "fullname": "Scott McTominay", "firstname": "Scott", "lastname": "McTominay", "nationality": "Scotland", "birthdate": "08/12/1996", "birthcountry": "England", "birthplace": "Lancaster", "height": "193 cm", "weight": "88 kg", "image_path": "https://cdn.sportmonks.com/images/soccer/players/16/455376.png"}, {"player_id": 1829, "team_id": 14, "country_id": 17, "position_id": 4, "common_name": "A. Martial", "display_name": "Anthony Martial", "fullname": "Anthony Martial", "firstname": "Anthony", "lastname": "Martial", "nationality": "France", "birthdate": "05/12/1995", "birthcountry": "France", "birthplace": "Massy", "height": "181 cm", "weight": "76 kg", "image_path": "https://cdn.sportmonks.com/images/soccer/players/5/1829.png"}, {"player_id": 1878, "team_id": 14, "country_id": 462, "position_id": 4, "common_name": "M. Rashford", "display_name": "Marcus Rashford", "fullname": "Marcus Rashford", "firstname": "Marcus", "lastname": "Rashford", "nationality": "England", "birthdate": "31/10/1997", "birthcountry": "England", "birthplace": "Manchester", "height": "180 cm", "weight": "70 kg", "image_path": "https://cdn.sportmonks.com/images//soccer/players/22/1878.png"}, {"player_id": 20333643, "team_id": 14, "country_id": 462, "position_id": 4, "common_name": "M. Greenwood", "display_name": "Mason Greenwood", "fullname": "Mason Greenwood", "firstname": "Mason", "lastname": "Greenwood", "nationality": "England", "birthdate": "01/10/2001", "birthcountry": "England", "birthplace": null, "height": null, "weight": null, "image_path": "https://cdn.sportmonks.com/images/soccer/players/11/20333643.png"}, {"player_id": 26031, "team_id": 14, "country_id": 38, "position_id": 3, "common_name": "D. van de Beek", "display_name": "Donny van de Beek", "fullname": "Donny van de Beek", "firstname": "Donny", "lastname": "van de Beek", "nationality": "Netherlands", "birthdate": "18/04/1997", "birthcountry": "Netherlands", "birthplace": "Nijkerkerveen", "height": "181 cm", "weight": "76 kg", "image_path": "https://cdn.sportmonks.com/images/soccer/players/15/26031.png"}, {"player_id": 12647, "team_id": 63, "country_id": 462, "position_id": 1, "common_name": "D. Henderson", "display_name": "Dean Henderson", "fullname": "Dean Henderson", "firstname": "Dean", "lastname": "Henderson", "nationality": "England", "birthdate": "12/03/1997", "birthcountry": "England", "birthplace": "Whitehaven", "height": "190 cm", "weight": "85 kg", "image_path": "https://cdn.sportmonks.com/images/soccer/players/7/12647.png"}, {"player_id": 130177, "team_id": 676, "country_id": 5, "position_id": 2, "common_name": "A. Telles", "display_name": "Alex Telles", "fullname": "Alex Nicolao Telles", "firstname": "Alex Nicolao", "lastname": "Telles", "nationality": "Brazil", "birthdate": "15/12/1992", "birthcountry": "Brazil", "birthplace": "Caxias do Sul", "height": "181 cm", "weight": "67 kg", "image_path": "https://cdn.sportmonks.com/images//soccer/players/1/130177.png"}, {"player_id": 96088, "team_id": 214, "country_id": 158, "position_id": 4, "common_name": "E. Cavani", "display_name": "Edinson Cavani", "fullname": "Edinson Roberto Cavani G\u00f3mez", "firstname": "Edinson Roberto", "lastname": "Cavani G\u00f3mez", "nationality": "Uruguay", "birthdate": "14/02/1987", "birthcountry": "Uruguay", "birthplace": "Salto", "height": "184 cm", "weight": "71 kg", "image_path": "https://cdn.sportmonks.com/images/soccer/players/24/96088.png"}, {"player_id": 37317015, "team_id": 3, "country_id": 23, "position_id": 4, "common_name": "A. Traor\u00e9", "display_name": "Amad Traor\u00e9", "fullname": "Amad Diallo Traor\u00e9", "firstname": "Amad Diallo", "lastname": "Traor\u00e9", "nationality": "C\u00f4te d'Ivoire", "birthdate": "11/07/2002", "birthcountry": "C\u00f4te d'Ivoire", "birthplace": null, "height": null, "weight": null, "image_path": "https://cdn.sportmonks.com/images/soccer/players/23/37317015.png"}, {"player_id": 27422646, "team_id": 236669, "country_id": 716, "position_id": 4, "common_name": "S. Shoretire", "display_name": "Shola Shoretire", "fullname": "Shola Shoretire", "firstname": "Shola", "lastname": "Shoretire", "nationality": "England", "birthdate": null, "birthcountry": "Nigeria", "birthplace": null, "height": null, "weight": null, "image_path": "https://cdn.sportmonks.com/images/soccer/players/22/27422646.png"}, {"player_id": 5283846, "team_id": 129, "country_id": 491, "position_id": 3, "common_name": "E. William Galbraith", "display_name": "Ethan Galbraith", "fullname": "Ethan Stuart William Galbraith", "firstname": "Ethan Stuart", "lastname": "William Galbraith", "nationality": "Northern Ireland", "birthdate": "11/05/2001", "birthcountry": "Northern Ireland", "birthplace": null, "height": null, "weight": null, "image_path": "https://cdn.sportmonks.com/images/soccer/placeholder.png"}, {"player_id": 28912805, "team_id": 14, "country_id": 47, "position_id": 4, "common_name": "A. Elanga", "display_name": "Anthony Elanga", "fullname": "Anthony Elanga", "firstname": "Anthony", "lastname": "Elanga", "nationality": "Sweden", "birthdate": "27/04/2002", "birthcountry": "Sweden", "birthplace": null, "height": null, "weight": null, "image_path": "https://cdn.sportmonks.com/images/soccer/players/5/28912805.png"}, {"player_id": 37316858, "team_id": 12, "country_id": 17, "position_id": 3, "common_name": "H. Mejbri", "display_name": "Hannibal Mejbri", "fullname": "Hannibal Mejbri", "firstname": "Hannibal", "lastname": "Mejbri", "nationality": "Tunisia", "birthdate": "21/01/2003", "birthcountry": "France", "birthplace": null, "height": null, "weight": null, "image_path": "https://cdn.sportmonks.com/images//soccer/players/26/37316858.png"}, {"player_id": 820, "team_id": 63, "country_id": 462, "position_id": 3, "common_name": "J. Lingard", "display_name": "Jesse Lingard", "fullname": "Jesse Lingard", "firstname": "Jesse", "lastname": "Lingard", "nationality": "England", "birthdate": "15/12/1992", "birthcountry": "England", "birthplace": "Warrington", "height": "175 cm", "weight": "62 kg", "image_path": "https://cdn.sportmonks.com/images/soccer/players/20/820.png"}, {"player_id": 1454, "team_id": 14, "country_id": 462, "position_id": 1, "common_name": "T. Heaton", "display_name": "Tom Heaton", "fullname": "Tom Heaton", "firstname": "Tom", "lastname": "Heaton", "nationality": "England", "birthdate": "15/04/1986", "birthcountry": "England", "birthplace": "Chester", "height": "188 cm", "weight": "85 kg", "image_path": "https://cdn.sportmonks.com/images//soccer/players/14/1454.png"}, {"player_id": 12759176, "team_id": 2727, "country_id": 245, "position_id": 1, "common_name": "M. Kov\u00e1\u0159", "display_name": "Matej Kovar", "fullname": "Mat\u011bj Kov\u00e1\u0159", "firstname": "Mat\u011bj", "lastname": "Kov\u00e1\u0159", "nationality": "Czech Republic", "birthdate": "17/05/2000", "birthcountry": "Czech Republic", "birthplace": null, "height": null, "weight": null, "image_path": "https://cdn.sportmonks.com/images/soccer/players/8/12759176.png"}, {"player_id": 164061, "team_id": 14, "country_id": 20, "position_id": 2, "common_name": "J. Dalot Teixeira", "display_name": "Diogo Dalot", "fullname": "Jos\u00e9 Diogo Dalot Teixeira", "firstname": "Jos\u00e9 Diogo", "lastname": "Dalot Teixeira", "nationality": "Portugal", "birthdate": "18/03/1999", "birthcountry": "Portugal", "birthplace": "Braga", "height": "184 cm", "weight": null, "image_path": "https://cdn.sportmonks.com/images/soccer/players/29/164061.png"}, {"player_id": 24469185, "team_id": 14, "country_id": 462, "position_id": 2, "common_name": "T. Mengi", "display_name": "Teden Mengi", "fullname": "Teden Mengi", "firstname": "Teden", "lastname": "Mengi", "nationality": "England", "birthdate": "30/04/2002", "birthcountry": "England", "birthplace": null, "height": null, "weight": null, "image_path": "https://cdn.sportmonks.com/images/soccer/players/1/24469185.png"}, {"player_id": 4536524, "team_id": 13, "country_id": 462, "position_id": 3, "common_name": "J. Garner", "display_name": "James Garner", "fullname": "James Garner", "firstname": "James", "lastname": "Garner", "nationality": "England", "birthdate": "13/03/2001", "birthcountry": "England", "birthplace": "Birkenhead", "height": null, "weight": null, "image_path": "https://cdn.sportmonks.com/images//soccer/players/12/4536524.png"}, {"player_id": 1004, "team_id": 11, "country_id": 5, "position_id": 3, "common_name": "A. Hoelgebaum Pereira", "display_name": "Andreas Pereira", "fullname": "Andreas Hoelgebaum Pereira", "firstname": "Andreas", "lastname": "Hoelgebaum Pereira", "nationality": "Brazil", "birthdate": "01/01/1996", "birthcountry": "Belgium", "birthplace": "Duffel", "height": "178 cm", "weight": "71 kg", "image_path": "https://cdn.sportmonks.com/images/soccer/players/12/1004.png"}, {"player_id": 7742181, "team_id": 282, "country_id": 515, "position_id": 3, "common_name": "D. Levitt", "display_name": "Dylan Levitt", "fullname": "Dylan Levitt", "firstname": "Dylan", "lastname": "Levitt", "nationality": "Wales", "birthdate": "17/11/2000", "birthcountry": "Wales", "birthplace": null, "height": null, "weight": null, "image_path": "https://cdn.sportmonks.com/images/soccer/players/5/7742181.png"}, {"player_id": 538034, "team_id": 14, "country_id": 462, "position_id": 4, "common_name": "J. Sancho", "display_name": "Jadon Sancho", "fullname": "Jadon Sancho", "firstname": "Jadon", "lastname": "Sancho", "nationality": "England", "birthdate": "25/03/2000", "birthcountry": "England", "birthplace": "London", "height": "180 cm", "weight": "76 kg", "image_path": "https://cdn.sportmonks.com/images/soccer/players/18/538034.png"}, {"player_id": 37341761, "team_id": 236669, "country_id": 462, "position_id": 3, "common_name": "J. Hugill", "display_name": "Joe Hugill", "fullname": "Joe Hugill", "firstname": "Joe", "lastname": "Hugill", "nationality": "England", "birthdate": null, "birthcountry": "England", "birthplace": null, "height": null, "weight": null, "image_path": "https://cdn.sportmonks.com/images/soccer/placeholder.png"}, {"player_id": 4601, "team_id": 3321, "country_id": 38, "position_id": 2, "common_name": "T. Fosu-Mensah", "display_name": "Timothy Fosu-Mensah", "fullname": "Timothy Evans Fosu-Mensah", "firstname": "Timothy Evans", "lastname": "Fosu-Mensah", "nationality": "Netherlands", "birthdate": "02/01/1998", "birthcountry": "Netherlands", "birthplace": "Amsterdam", "height": "190 cm", "weight": "78 kg", "image_path": "https://cdn.sportmonks.com/images//soccer/players/25/4601.png"}, {"player_id": 1248, "team_id": 7011, "country_id": 716, "position_id": 4, "common_name": "O. Ighalo", "display_name": "Odion Ighalo", "fullname": "Odion Jude Ighalo", "firstname": "Odion Jude", "lastname": "Ighalo", "nationality": "Nigeria", "birthdate": "16/06/1989", "birthcountry": "Nigeria", "birthplace": "Lagos", "height": "188 cm", "weight": "73 kg", "image_path": "https://cdn.sportmonks.com/images/soccer/players/0/1248.png"}, {"player_id": 10907, "team_id": 236669, "country_id": 462, "position_id": 1, "common_name": "N. Bishop", "display_name": "Nathan Bishop", "fullname": "Nathan Bishop", "firstname": "Nathan", "lastname": "Bishop", "nationality": "England", "birthdate": "15/10/1999", "birthcountry": "England", "birthplace": "Hillingdon", "height": "185 cm", "weight": "72 kg", "image_path": "https://cdn.sportmonks.com/images/soccer/players/27/10907.png"}, {"player_id": 27422645, "team_id": 66, "country_id": 462, "position_id": 2, "common_name": "W. Fish", "display_name": "William Fish", "fullname": "William Fish", "firstname": "William", "lastname": "Fish", "nationality": "England", "birthdate": "17/02/2003", "birthcountry": "England", "birthplace": null, "height": null, "weight": null, "image_path": "https://cdn.sportmonks.com/images/soccer/placeholder.png"}]